{
  "months": {
    "1": "1_Befana.webp",
    "12": "12_Babbo Natale.webp",
    "2": "2_Cupido.webp",
    "3": "3_Rondine.webp",
    "8": "8_Ombrellone.webp"
  },
  "numbers": {
    "0": "0_Sci.webp",
    "00": "00_Sasso.webp",
    "01": "01_Sedia.webp",
    "02": "02_Zaino.webp",
    "03": "03_Seme.webp",
    "04": "04_Suora.webp",
    "05": "05_Sella.webp",
    "06": "06_Saggio.webp",
    "07": "07_Sacco.webp",
    "08": "08_Soffio.webp",
    "09": "09_Seppia.webp",
    "1": "1_Te\u0300.webp",
    "10": "10_Tasso.webp",
    "11": "11_Dadi.webp",
    "12": "12_Tana.webp",
    "13": "13_Dama.webp",
    "14": "14_Terra.webp",
    "15": "15_Teglia.webp",
    "16": "16_Doccia.webp",
    "17": "17_Tacco.webp",
    "18": "18_Tv.webp",
    "19": "19_Tappo.webp",
    "2": "2_Neo (Matrix).webp",
    "20": "20_Naso.webp",
    "21": "21_Nodo.webp",
    "22": "22_Nonni.webp",
    "23": "23_Nemo.webp",
    "24": "24_Nero.webp",
    "25": "25_Anello.webp",
    "26": "26_Noce.webp",
    "27": "27_Gnocchi.webp",
    "28": "28_Nave.webp",
    "29": "29_Nebbia.webp",
    "3": "3_Amo.webp",
    "30": "30_Mazza.webp",
    "31": "31_Moto.webp",
    "32": "32_Mano (Addams).webp",
    "33": "33_Mamma.webp",
    "34": "34_More.webp",
    "35": "35_Mela.webp",
    "36": "36_Micio.webp",
    "37": "37_Amaca.webp",
    "38": "38_Muffa.webp",
    "39": "39_Mappa.webp",
    "4": "4_Oro.webp",
    "40": "40_Orso.webp",
    "41": "41_Rete.webp",
    "42": "42_Rana.webp",
    "43": "43_Orma.webp",
    "44": "44_Orrore.webp",
    "45": "45_Rullo (macchinario).webp",
    "46": "46_Riccio.webp",
    "47": "47_Arco.webp",
    "48": "48_Riva.webp",
    "49": "49_Rapa.webp",
    "5": "5_Ali.webp",
    "50": "50_Lessie.webp",
    "51": "51_Letto.webp",
    "52": "52_Luna.webp",
    "53": "53_Lama.webp",
    "54": "54_Lara.webp",
    "55": "55_Lilli.webp",
    "56": "56_Luce.webp",
    "57": "57_Lago.webp",
    "58": "58_Lava.webp",
    "59": "59_Lupo.webp",
    "6": "6_Ace.webp",
    "60": "60_Cesso.webp",
    "61": "61_CD.webp",
    "62": "62_Genio.webp",
    "63": "63_Gomma.webp",
    "64": "64_Cero.webp",
    "65": "65_Cielo.webp",
    "66": "66_Ciuccio.webp",
    "67": "67_Giacca.webp",
    "68": "68_Giove.webp",
    "69": "69_Jeep.webp",
    "7": "7_Oca.webp",
    "70": "70_Cassa.webp",
    "71": "71_Coda.webp",
    "72": "72_Cono (gelato).webp",
    "73": "73_Gomma.webp",
    "74": "74_Cuore.webp",
    "75": "75_Collo.webp",
    "76": "76_Goccia.webp",
    "77": "77_Cacca.webp",
    "78": "78_Caffe.webp",
    "79": "79_Coppa.webp",
    "8": "8_Ufo.webp",
    "80": "80_Vaso.webp",
    "81": "81_Foto.webp",
    "82": "82_Vino.webp",
    "83": "83_Fiamme.webp",
    "84": "84_Faro.webp",
    "85": "85_Vela.webp",
    "86": "86_Faccia.webp",
    "87": "87_Fico.webp",
    "88": "88_Fave.webp",
    "89": "89_Fibbia.webp",
    "9": "9_Ape.webp",
    "90": "90_Pizza.webp",
    "91": "91_Piede.webp",
    "92": "92_Penna.webp",
    "93": "93_Piuma.webp",
    "94": "94_Burro.webp",
    "95": "95_Palla.webp",
    "96": "96_Bici.webp",
    "97": "97_Bocca.webp",
    "98": "98_Baffo.webp",
    "99": "99_Papa.webp"
  },
  "letters_upper": {
    "A": "A_Aereo.webp",
    "B": "B_Balena.webp",
    "C": "C_Cannone.webp",
    "D": "D_Dromedario.webp",
    "E": "E_Elefante.webp",
    "F": "F_Fucile.webp",
    "G": "G_Gru.webp",
    "H": "H_Hotel.webp",
    "I": "I_Ippopotamo.webp",
    "J": "J_Jeans.webp",
    "K": "K_King Kong.webp",
    "L": "L_Lampione.webp",
    "M": "M_Maiale.webp",
    "O": "O_Orca.webp",
    "P": "P_Ptedorattilo.webp",
    "Q": "Q_Quercia.webp",
    "R": "R_Rinoceronte.webp",
    "S": "S_Struzzo.webp",
    "T": "T_Trattore.webp",
    "U": "U_Umarell.webp",
    "V": "V_Velociraptor.webp",
    "X": "X_Professor X.webp",
    "Y": "Y_Yeti.webp",
    "Z": "Z_Zebra.webp"
  },
  "symbols": {
    "radice": "radice_quadrata.webp"
  },
  "letters_lower": {
    "a": "a_Accendino.webp",
    "b": "b_Bottone.webp",
    "c": "c_Caramella.webp",
    "d": "d_Dente.webp",
    "e": "e_Elmo.webp",
    "f": "f_Formica.webp",
    "g": "g_Gufo.webp",
    "h": "h_Hot Dog.webp",
    "i": "i_Iguana.webp",
    "j": "j_Joystick.webp",
    "k": "k_Kiwi (animale).webp",
    "l": "l_Lumaca.webp",
    "m": "m_Marmotta.webp",
    "n": "n_Nacchere.webp",
    "o": "o_Occhiali.webp",
    "p": "p_Proiettile.webp",
    "q": "q_Quadrifoglio.webp",
    "r": "r_Rosa.webp",
    "s": "s_Scarabeo.webp",
    "t": "t_Trapano.webp",
    "u": "u_Uovo.webp",
    "v": "v_Vite.webp",
    "w": "w_Walkman.webp",
    "x": "x_Xilofono.webp",
    "y": "y_Yogurt.webp",
    "z": "z_Zanzara.webp"
  }
}